cbmos/__init__.py
cbmos/cell.py
cbmos/events.py
cbmos/force_functions.py
cbmos/cbmodel/__init__.py
cbmos/cbmodel/_eventqueue.py
cbmos/solvers/__init__.py
cbmos/solvers/adams_bashforth.py
cbmos/solvers/euler_backward.py
cbmos/solvers/euler_forward.py
cbmos/solvers/geshgorin.py
cbmos/solvers/heun.py
cbmos/solvers/midpoint.py
cbmos/utils/__init__.py
cbmos-0.3.0.dist-info/LICENSE.txt
cbmos-0.3.0.dist-info/METADATA
cbmos-0.3.0.dist-info/WHEEL
cbmos-0.3.0.dist-info/top_level.txt
cbmos-0.3.0.dist-info/RECORD
