Metadata-Version: 2.1
Name: cbmos
Version: 0.3.0
Summary: A framework for numerical analysis of center-based cell models
Home-page: https://github.com/somathias/cbmos
Author: Sonja Mathias et al.
Author-email: sonja.mathias@it.uu.se
Project-URL: Bug Tracker, https://github.com/somathias/cbmos/issues
Classifier: Programming Language :: Python :: 3
Classifier: License :: OSI Approved :: MIT License
Classifier: Operating System :: OS Independent
License-File: LICENSE.txt
Requires-Dist: numpy (>=1.18)
Requires-Dist: scipy (>=1.4.0)
Requires-Dist: parse
Requires-Dist: matplotlib
Provides-Extra: gpu
Requires-Dist: cupy ; extra == 'gpu'
